[
  {
    "id": "recipe_20241124_132750",
    "content": "Title: 烤串\nChinese Name: 烤羊肉串\nEnglish Name: 烤羊肉串\nCuisine Type: 新疆菜\n\n烤串，或称烤串儿、串燒，指将肉类、蔬菜等食材用签子穿成串后炙烤的烹饪方法，也指通过该方法产生的食物，属于烧烤的一种。烤串在中东、南亚、中亚、地中海、东亚等多地均非常流行。 作为一種起源于中东，後來流傳至南亚及地中海地區，後至全世界的料理。卡博（Kebabı）的意思是在中東一帶燒、煎和烤的肉類料理總稱（不一定是串起來的肉類，主要為雞肉、羊肉、牛肉、駱駝肉，沒有豬肉）。這個詞源於波斯語的“کباب‎”（Kebab），意思原指「烤肉」。",
    "metadata": {
      "cuisine_type": "新疆菜",
      "dish_name": "烤羊肉串",
      "english_name": "烤羊肉串",
      "source": "wikipedia",
      "source_url": "https://zh.wikipedia.org/wiki/%E7%83%A4%E4%B8%B2",
      "timestamp": "2024-11-24T13:27:50.988190"
    }
  },
  {
    "id": "recipe_20241124_132752",
    "content": "Title: 馕\nChinese Name: 馕\nEnglish Name: 馕\nCuisine Type: 新疆菜\n\n馕（波斯語：نان‎、印地語：नान、哈薩克語：нан, nan、維吾爾語：نان‎、塔吉克語：Нон），是一种起源于波斯的发酵面饼，是伊朗、中亚、中国新疆以及南亚一些民族的主食之一。在移民的影响下，馕也传到了波斯湾地区、欧洲和北美。馕的制作方法是将面团和好发酵后，在特制的馕坑中烤製而成。具体形状因地域和民族习惯而不同，有擀制的面饼，有盘起成半球状的面团，也有直接拿手拉拽成长面片的。由于可以存放很长时间不坏，馕也可以作为便携干粮。它吃起来口感很酥脆而且也可有多种口味，这不仅仅是一种食物，也是一种文化的传承。 制作讲究的馕中间会拓上花纹，并撒上芝麻、洋葱末。和面的时候要加入烹调用油、也可加入鸡蛋、牛奶或者酸奶，使得烤出来的馕喷香酥脆可口。烤製的时候，还可以加上葡萄乾。以维吾尔馕为例，形状有基本的圆形，也有葡萄形、哈密瓜形等。新疆馕的种类还包括油馕、窝窝馕、玉米馕、白皮馕等等。伊朗和阿富汗的哈扎拉人制作的馕则多为用手拉扯成较长的面片，直接拍在馕坑上。印度的馕则包括大蒜黄油馕、印度奶酪馕等。 馕坑是用于烤制馕的烤炉，用盐土制成，分为地上和地下两类。地下馕坑如同浅井，地上馕坑的整体如同一只倒扣在地上的碗，底大口小。",
    "metadata": {
      "cuisine_type": "新疆菜",
      "dish_name": "馕",
      "english_name": "馕",
      "source": "wikipedia",
      "source_url": "https://zh.wikipedia.org/wiki/%E9%A6%95",
      "timestamp": "2024-11-24T13:27:52.922963"
    }
  },
  {
    "id": "recipe_20241124_132754",
    "content": "Title: 抓饭\nChinese Name: 羊肉抓饭\nEnglish Name: 羊肉抓饭\nCuisine Type: 新疆菜\n\n抓饭，也叫香料饭，是西亞、中亞、南亚等地的传统食物，也是中亚族群的标志性食物。不同地方的手抓飯有不同的風味，除了用料不同外，佐料也是主要原因。常見的特徵包括用湯來煮米飯（或其他穀物）、加入香料、肉、蔬菜和果乾，並追求讓米粒分開而不是黏在一起。",
    "metadata": {
      "cuisine_type": "新疆菜",
      "dish_name": "羊肉抓饭",
      "english_name": "羊肉抓饭",
      "source": "wikipedia",
      "source_url": "https://zh.wikipedia.org/wiki/%E6%8A%93%E9%A5%AD",
      "timestamp": "2024-11-24T13:27:54.438414"
    }
  },
  {
    "id": "recipe_20241124_132755",
    "content": "Title: 拌麵\nChinese Name: 过油肉拌面\nEnglish Name: 过油肉拌面\nCuisine Type: 新疆菜\n\n拌麵，又稱乾拌麵，粵語及臺灣國語稱作撈麵，是指把瀝乾的麵條拌以醬料（或其他调味料）一起食用的吃法。 拌麵在宋朝就有出現，據《东京梦华录》、《梦梁录》、《武林旧事》等書就有混合醬汁、肉的拌肉麵。",
    "metadata": {
      "cuisine_type": "新疆菜",
      "dish_name": "过油肉拌面",
      "english_name": "过油肉拌面",
      "source": "wikipedia",
      "source_url": "https://zh.wikipedia.org/wiki/%E6%8B%8C%E9%BA%B5",
      "timestamp": "2024-11-24T13:27:55.989988"
    }
  },
  {
    "id": "recipe_20241124_132757",
    "content": "Title: 菠菜\nChinese Name: 菠菜面\nEnglish Name: 菠菜面\nCuisine Type: 新疆菜\n\n菠菜（學名：Spinacia oleracea），又名菠薐、鹦鹉菜、红根菜及飛龍菜，是莧科菠菜属的一年或二年生草本植物。性喜冷凉气候，耐寒性强，适于沙壤或粘土壤生长，根和叶子可以食用。菠菜于7世纪左右由尼泊尔传入中国，现已是一道家常菜。菠菜于14世纪左右传入英格兰。菠菜常用来煲汤，凉拌，单炒，和配荤菜合炒或火鍋垫盘。 菠菜一年四季都可以收获，通常春天的菠菜比较嫩小，适合凉拌，而秋天的粗大，比较适合熟食。但是现在有很多温室培养的菠菜，一年到头都是一样的。",
    "metadata": {
      "cuisine_type": "新疆菜",
      "dish_name": "菠菜面",
      "english_name": "菠菜面",
      "source": "wikipedia",
      "source_url": "https://zh.wikipedia.org/wiki/%E8%8F%A0%E8%8F%9C",
      "timestamp": "2024-11-24T13:27:57.589228"
    }
  },
  {
    "id": "recipe_20241124_132759",
    "content": "Title: 拉条子\nChinese Name: 拉条子\nEnglish Name: 拉条子\nCuisine Type: 新疆菜\n\n拉条子，又称拉条兒、拌麵，在中亚地区则称为拉麵（維吾爾語：لەڭمەن‎、吉爾吉斯語：لەغمەن，哈薩克語：лағман，音译为拉格曼），源自汉语“拉面”，是甘肅、新疆等中国西北地区以及中亚地区的主食之一。通常选用精白麵加水和制，面团要软硬适度，太软、太硬都不行，面团要多揉，揉出筋道，然后切成细条拉开入沸水煮熟即可食用。多为清真食品。 拌麵的菜可根据个人的喜好选择。新疆人最喜欢吃的拌麵菜是“過油肉拌麵”：选用羊肉揉入淀粉过油，加青椒、番茄、洋葱（新疆人称皮芽子，源自波斯語پیاز‎，甘肅人稱洋蒜）、蒜炒熟佐面。也可直接与面条炒为一盘。菜品红、绿、白相间，香辣可口。",
    "metadata": {
      "cuisine_type": "新疆菜",
      "dish_name": "拉条子",
      "english_name": "拉条子",
      "source": "wikipedia",
      "source_url": "https://zh.wikipedia.org/wiki/%E6%8B%89%E6%9D%A1%E5%AD%90",
      "timestamp": "2024-11-24T13:27:59.105914"
    }
  },
  {
    "id": "recipe_20241124_132800",
    "content": "Title: 大盘鸡\nChinese Name: 大盘鸡\nEnglish Name: 大盘鸡\nCuisine Type: 新疆菜\n\n大盘鸡（維吾爾語：چوڭ تەخسە توخۇ قورۇمىسى‎，拉丁维文：qong təhsə tohu ⱪorumisi），又称沙湾大盘鸡、新疆大盘鸡，是一道主要用鸡肉、土豆、辣椒制作的炒菜，于1990年代左右由新疆塔城地区沙湾县厨师李士林创制，后又改变主料衍生出大盘肚、大盘鱼、大盘鸭、大盘鹅、大盤兔、大盘排骨等菜色。 与大盘鸡搭配食用的主食为皮带面。",
    "metadata": {
      "cuisine_type": "新疆菜",
      "dish_name": "大盘鸡",
      "english_name": "大盘鸡",
      "source": "wikipedia",
      "source_url": "https://zh.wikipedia.org/wiki/%E5%A4%A7%E7%9B%98%E9%B8%A1",
      "timestamp": "2024-11-24T13:28:00.632106"
    }
  },
  {
    "id": "recipe_20241124_132802",
    "content": "Title: 炒面\nChinese Name: 干煸炒面\nEnglish Name: 干煸炒面\nCuisine Type: 新疆菜\n\n炒麵，是指將麵條快炒出來的麵類料理，口味以酱油為主，有时会加些火腿，主要分为上海炒麵、廣東炒麵和日式炒麵。",
    "metadata": {
      "cuisine_type": "新疆菜",
      "dish_name": "干煸炒面",
      "english_name": "干煸炒面",
      "source": "wikipedia",
      "source_url": "https://zh.wikipedia.org/wiki/%E7%82%92%E9%9D%A2",
      "timestamp": "2024-11-24T13:28:02.313772"
    }
  },
  {
    "id": "recipe_20241124_132803",
    "content": "Title: 达瓦孜\nChinese Name: 新疆架子肉\nEnglish Name: 新疆架子肉\nCuisine Type: 新疆菜\n\n达瓦孜（維吾爾語：دارۋاز‎，拉丁维文：darwaz）是流传于中华人民共和国新疆维吾尔自治区维吾尔居民中的走钢丝杂技。一般在古尔邦节、诺鲁孜节等重大节日时表演。是中华人民共和国国家级非物质文化遗产代表性项目。其传承人为阿迪力·吾守尔。",
    "metadata": {
      "cuisine_type": "新疆菜",
      "dish_name": "新疆架子肉",
      "english_name": "新疆架子肉",
      "source": "wikipedia",
      "source_url": "https://zh.wikipedia.org/wiki/%E8%BE%BE%E7%93%A6%E5%AD%9C",
      "timestamp": "2024-11-24T13:28:03.783549"
    }
  },
  {
    "id": "recipe_20241124_132805",
    "content": "Title: 炒面\nChinese Name: 丁丁炒面\nEnglish Name: 丁丁炒面\nCuisine Type: 新疆菜\n\n炒麵，是指將麵條快炒出來的麵類料理，口味以酱油為主，有时会加些火腿，主要分为上海炒麵、廣東炒麵和日式炒麵。",
    "metadata": {
      "cuisine_type": "新疆菜",
      "dish_name": "丁丁炒面",
      "english_name": "丁丁炒面",
      "source": "wikipedia",
      "source_url": "https://zh.wikipedia.org/wiki/%E7%82%92%E9%9D%A2",
      "timestamp": "2024-11-24T13:28:05.300396"
    }
  },
  {
    "id": "recipe_20241124_132806",
    "content": "Title: 辣子鸡\nChinese Name: 辣子鸡丁\nEnglish Name: 辣子鸡丁\nCuisine Type: 川菜（四川，重庆）\n\n辣子鸡，又名辣子鸡丁，起源于重庆，所以也称重庆辣子鸡或歌乐山辣子鸡，是下河帮川菜的辣子系列代表。",
    "metadata": {
      "cuisine_type": "川菜（四川，重庆）",
      "dish_name": "辣子鸡丁",
      "english_name": "辣子鸡丁",
      "source": "wikipedia",
      "source_url": "https://zh.wikipedia.org/wiki/%E8%BE%A3%E5%AD%90%E9%B8%A1",
      "timestamp": "2024-11-24T13:28:06.790758"
    }
  },
  {
    "id": "recipe_20241124_132808",
    "content": "Title: 青椒肉絲\nChinese Name: 青椒肉丝\nEnglish Name: 青椒肉丝\nCuisine Type: 川菜（四川，重庆）\n\n青椒肉絲為一種將切絲的青椒和切絲的肉混合炒成的中国菜，也是四川菜和闽南菜在世界上代表性菜色之一，随着中国菜的在世界上的传播，目前青椒肉絲已經深深的滲透入了美国，日本等國家的日常飲食之中。",
    "metadata": {
      "cuisine_type": "川菜（四川，重庆）",
      "dish_name": "青椒肉丝",
      "english_name": "青椒肉丝",
      "source": "wikipedia",
      "source_url": "https://zh.wikipedia.org/wiki/%E9%9D%92%E6%A4%92%E8%82%89%E7%B5%B2",
      "timestamp": "2024-11-24T13:28:08.239952"
    }
  },
  {
    "id": "recipe_20241124_132809",
    "content": "Title: 鴨肉\nChinese Name: 啤酒鸭\nEnglish Name: 啤酒鸭\nCuisine Type: 川菜（四川，重庆）\n\n鴨肉，是從鴨身上取得的肉，為全世界普遍的肉品之一。鴨子是僅次於雞、世界上第二常被屠宰取肉的水生動物，在2013年，全球有超過二十八億隻鴨被屠宰取肉。在烹飪和美食中，鴨肉或小鴨是鴨科中幾種鳥類的肉，存在於淡水和鹽水中。 鴨在世界各地的許多美食中都可以食用。 它是富含鐵的高脂肪，高蛋白肉。 小鴨名義上來自幼小動物，但可能只是菜單名稱。",
    "metadata": {
      "cuisine_type": "川菜（四川，重庆）",
      "dish_name": "啤酒鸭",
      "english_name": "啤酒鸭",
      "source": "wikipedia",
      "source_url": "https://zh.wikipedia.org/wiki/%E9%B4%A8%E8%82%89",
      "timestamp": "2024-11-24T13:28:09.709474"
    }
  },
  {
    "id": "recipe_20241124_132811",
    "content": "Title: 水煮肉片\nChinese Name: 水煮肉片\nEnglish Name: 水煮肉片\nCuisine Type: 川菜（四川，重庆）\n\n水煮肉片是川菜的一种传统菜式，源自盐帮菜「水煮牛肉」，是在鹽幫下層工人中形成的，几乎四川家家户户都会做，其特色是“麻、辣、鲜、烫”。",
    "metadata": {
      "cuisine_type": "川菜（四川，重庆）",
      "dish_name": "水煮肉片",
      "english_name": "水煮肉片",
      "source": "wikipedia",
      "source_url": "https://zh.wikipedia.org/wiki/%E6%B0%B4%E7%85%AE%E8%82%89%E7%89%87",
      "timestamp": "2024-11-24T13:28:11.436286"
    }
  },
  {
    "id": "recipe_20241124_132812",
    "content": "Title: 火鍋\nChinese Name: 四川火锅\nEnglish Name: 四川火锅\nCuisine Type: 川菜（四川，重庆）\n\n火鍋，粤语称作打边炉，是一種以鍋現場加熱湯或水涮煮食物的烹調方式。其特色為即煮即吃，因此進食之時食物仍然熱氣騰騰。典型的火鍋材料包括：肉片、內臟、海鮮、蔬菜、蘑菇、豆腐、肉丸、即食麵、粉絲等，將它們放入煮開的湯底燙熟後食用。有些吃法還會蘸上調味料。",
    "metadata": {
      "cuisine_type": "川菜（四川，重庆）",
      "dish_name": "四川火锅",
      "english_name": "四川火锅",
      "source": "wikipedia",
      "source_url": "https://zh.wikipedia.org/wiki/%E7%81%AB%E9%8D%8B",
      "timestamp": "2024-11-24T13:28:12.937323"
    }
  },
  {
    "id": "recipe_20241124_132814",
    "content": "Title: 宫保鸡丁\nChinese Name: 宫保鸡丁\nEnglish Name: 宫保鸡丁\nCuisine Type: 川菜（四川，重庆）\n\n宫保鸡丁（英语：Kung Pao chicken），呈糊辣荔枝味，是源於黔菜、流傳至魯而後成於川菜的一道川味菜餚。贵州、山东和四川三地对这道菜的做法不完全一样，称呼也有差异。贵州稱為糊辣子鸡丁，山东则名為酱爆鸡丁，而四川就是以宫保鸡丁為名。",
    "metadata": {
      "cuisine_type": "川菜（四川，重庆）",
      "dish_name": "宫保鸡丁",
      "english_name": "宫保鸡丁",
      "source": "wikipedia",
      "source_url": "https://zh.wikipedia.org/wiki/%E5%AE%AB%E4%BF%9D%E9%B8%A1%E4%B8%81",
      "timestamp": "2024-11-24T13:28:14.422602"
    }
  },
  {
    "id": "recipe_20241124_132815",
    "content": "Title: 酸菜鱼\nChinese Name: 酸菜鱼\nEnglish Name: 酸菜鱼\nCuisine Type: 川菜（四川，重庆）\n\n酸菜鱼，是起源于重庆的一道知名菜色，做法有多种，主要原料为草鱼、酸菜、泡辣椒、花椒、生薑或泡薑等。 酸菜鱼与水煮鱼一样，风靡中国各地。虽然都是以切成片的鱼肉作为主料，但酸菜鱼和水煮鱼的做法却有所不同。酸菜鱼是将泡椒、姜等炒出香味，再加汤炖煮酸菜和鱼；水煮鱼则为将鱼肉焯烫后，将炒入乾辣椒、花椒等调料的热油浇在鱼肉上，口感上帶著點椒麻微辣感，湯汁酸辣香濃，現在已經是兩岸四地相當熱門的料理。",
    "metadata": {
      "cuisine_type": "川菜（四川，重庆）",
      "dish_name": "酸菜鱼",
      "english_name": "酸菜鱼",
      "source": "wikipedia",
      "source_url": "https://zh.wikipedia.org/wiki/%E9%85%B8%E8%8F%9C%E9%B1%BC",
      "timestamp": "2024-11-24T13:28:15.919116"
    }
  },
  {
    "id": "recipe_20241124_132817",
    "content": "Title: 炒泡麵\nChinese Name: 辣椒炒肉\nEnglish Name: 辣椒炒肉\nCuisine Type: 川菜（四川，重庆）\n\n炒即食麵為香港、臺灣、福建以及新馬、印尼、南韓等地的平民食品，其中炒公仔麵是香港的特色食品，最初在香港的茶餐廳出現，如今已在大部分香港餐廳普及。而在厦门，當地的炒泡面原名是“双山牌”沙嗲味即食伊面，但由於包裝上的“厦门泡面”字樣較為醒目，多數人忽略了其原名“即食伊面”。",
    "metadata": {
      "cuisine_type": "川菜（四川，重庆）",
      "dish_name": "辣椒炒肉",
      "english_name": "辣椒炒肉",
      "source": "wikipedia",
      "source_url": "https://zh.wikipedia.org/wiki/%E7%82%92%E6%B3%A1%E9%BA%B5",
      "timestamp": "2024-11-24T13:28:17.632750"
    }
  },
  {
    "id": "recipe_20241124_132820",
    "content": "Title: 麻辣烫\nChinese Name: 麻辣烫\nEnglish Name: 麻辣烫\nCuisine Type: 川菜（四川，重庆）\n\n麻辣烫，是一种起源于中国四川省乐山市，流行各地的小吃，其味道麻辣鲜香，主要在街头常见。部分地区的麻辣烫由于当地人口味的原因会和传统的麻辣烫有所不同。",
    "metadata": {
      "cuisine_type": "川菜（四川，重庆）",
      "dish_name": "麻辣烫",
      "english_name": "麻辣烫",
      "source": "wikipedia",
      "source_url": "https://zh.wikipedia.org/wiki/%E9%BA%BB%E8%BE%A3%E7%83%AB",
      "timestamp": "2024-11-24T13:28:20.358353"
    }
  },
  {
    "id": "recipe_20241124_132822",
    "content": "Title: 毛血旺\nChinese Name: 毛血旺\nEnglish Name: 毛血旺\nCuisine Type: 川菜（四川，重庆）\n\n毛血旺，又稱冒血旺，是一道川菜，起源於重慶磁器口古镇的小吃。「毛」是重慶方言，意为粗獷、馬虎。且有毛肚百葉等雜碎為主料，所以「毛血旺」菜名廣為流傳。",
    "metadata": {
      "cuisine_type": "川菜（四川，重庆）",
      "dish_name": "毛血旺",
      "english_name": "毛血旺",
      "source": "wikipedia",
      "source_url": "https://zh.wikipedia.org/wiki/%E6%AF%9B%E8%A1%80%E6%97%BA",
      "timestamp": "2024-11-24T13:28:22.056161"
    }
  },
  {
    "id": "recipe_20241124_132823",
    "content": "Title: 冒菜\nChinese Name: 冒菜\nEnglish Name: 冒菜\nCuisine Type: 川菜（四川，重庆）\n\n冒菜是一种成都小吃，制作方法是将预备好的蔬菜和肉放入辣味底料汤汁中烫熟后食用，有麻辣和香辣。",
    "metadata": {
      "cuisine_type": "川菜（四川，重庆）",
      "dish_name": "冒菜",
      "english_name": "冒菜",
      "source": "wikipedia",
      "source_url": "https://zh.wikipedia.org/wiki/%E5%86%92%E8%8F%9C",
      "timestamp": "2024-11-24T13:28:23.545284"
    }
  },
  {
    "id": "recipe_20241124_132825",
    "content": "Title: 口水雞\nChinese Name: 口水鸡\nEnglish Name: 口水鸡\nCuisine Type: 川菜（四川，重庆）\n\n口水雞是四川常见的冷盤食品。属于川菜的一种。",
    "metadata": {
      "cuisine_type": "川菜（四川，重庆）",
      "dish_name": "口水鸡",
      "english_name": "口水鸡",
      "source": "wikipedia",
      "source_url": "https://zh.wikipedia.org/wiki/%E5%8F%A3%E6%B0%B4%E9%9B%9E",
      "timestamp": "2024-11-24T13:28:25.018260"
    }
  },
  {
    "id": "recipe_20241124_132826",
    "content": "Title: 回锅肉\nChinese Name: 回锅肉\nEnglish Name: 回锅肉\nCuisine Type: 川菜（四川，重庆）\n\n回锅肉，川西地区称之为熬锅肉，是中國川菜中一種烹調豬肉的传统菜式。 回鍋肉的做法非常多樣，即使是在發源地四川也有各種不同的版本，另外，這道菜在美國、日本和韓國也發展出獨特的口味。",
    "metadata": {
      "cuisine_type": "川菜（四川，重庆）",
      "dish_name": "回锅肉",
      "english_name": "回锅肉",
      "source": "wikipedia",
      "source_url": "https://zh.wikipedia.org/wiki/%E5%9B%9E%E9%94%85%E8%82%89",
      "timestamp": "2024-11-24T13:28:26.681357"
    }
  },
  {
    "id": "recipe_20241124_132828",
    "content": "Title: 冰粉\nChinese Name: 四川冰粉\nEnglish Name: 四川冰粉\nCuisine Type: 川菜（四川，重庆）\n\n冰粉是一种流行于中国西南地区，用石花树（或称冰粉树）的籽凝结制作而成的食品，口味以甜为主。在湖北的宜昌荆州地区，以石花树的名字命名冰粉为石花，命名方式与台湾的爱玉类似。",
    "metadata": {
      "cuisine_type": "川菜（四川，重庆）",
      "dish_name": "四川冰粉",
      "english_name": "四川冰粉",
      "source": "wikipedia",
      "source_url": "https://zh.wikipedia.org/wiki/%E5%86%B0%E7%B2%89",
      "timestamp": "2024-11-24T13:28:28.199451"
    }
  },
  {
    "id": "recipe_20241124_132829",
    "content": "Title: 麻辣火鍋\nChinese Name: 重庆火锅\nEnglish Name: 重庆火锅\nCuisine Type: 川菜（四川，重庆）\n\n麻辣火鍋傳說為起源于中国川渝地区的菜餚，一般以花椒粒、蔥段、薑片，辣椒粉、紫草、桂皮、八角、大小茴香等熬製而成。吃時舌頭微感麻痺，味帶辛辣，故名為麻辣火鍋。",
    "metadata": {
      "cuisine_type": "川菜（四川，重庆）",
      "dish_name": "重庆火锅",
      "english_name": "重庆火锅",
      "source": "wikipedia",
      "source_url": "https://zh.wikipedia.org/wiki/%E9%BA%BB%E8%BE%A3%E7%81%AB%E9%8D%8B",
      "timestamp": "2024-11-24T13:28:29.676500"
    }
  },
  {
    "id": "recipe_20241124_132831",
    "content": "Title: 水煮鱼\nChinese Name: 水煮鱼\nEnglish Name: 水煮鱼\nCuisine Type: 西北菜 （陕西，甘肃等地）\n\n水煮鱼又称水煮鱼片、水煮活魚，起源于重庆的火锅鱼，是重庆江湖菜的代表。 渝派川菜的一种，做法有多种，主要原料是草鱼或黑鱼、乾辣椒节、花椒，也有不放花椒的，有的配上豆芽等蔬菜，烧制方法是将鱼片放入开水中，快速烧煮，而后装盆，淋上含有爆香了的辣椒花椒等调料的滚油。 水煮鱼片的口味偏嫩、辣，放花椒的则还很麻，是大街小巷的饭馆里面常见的一道川菜。在北方地区，为了迎合当地市场与饮食习惯，水煮鱼中的辣椒和花椒都在装盆时被捞出。",
    "metadata": {
      "cuisine_type": "西北菜 （陕西，甘肃等地）",
      "dish_name": "水煮鱼",
      "english_name": "水煮鱼",
      "source": "wikipedia",
      "source_url": "https://zh.wikipedia.org/wiki/%E6%B0%B4%E7%85%AE%E9%B1%BC",
      "timestamp": "2024-11-24T13:28:31.177970"
    }
  },
  {
    "id": "recipe_20241124_132832",
    "content": "Title: 米皮\nChinese Name: 米皮\nEnglish Name: 米皮\nCuisine Type: 西北菜 （陕西，甘肃等地）\n\n米皮，是中國陝西、河南、甘肃一帶的一種特色小吃，以米浆为主要原料，通过一系列的蒸制加工而成，一般用豆芽及黄瓜丝作为菜码，调上香醋及油泼辣子，以秦镇米皮、汉中米皮、武都米皮、文县米皮最為聞名。",
    "metadata": {
      "cuisine_type": "西北菜 （陕西，甘肃等地）",
      "dish_name": "米皮",
      "english_name": "米皮",
      "source": "wikipedia",
      "source_url": "https://zh.wikipedia.org/wiki/%E7%B1%B3%E7%9A%AE",
      "timestamp": "2024-11-24T13:28:32.958344"
    }
  },
  {
    "id": "recipe_20241124_132834",
    "content": "Title: 凉皮\nChinese Name: 酿皮\nEnglish Name: 酿皮\nCuisine Type: 西北菜 （陕西，甘肃等地）\n\n凉皮又称皮子、酿皮子、麵皮、擀面皮、米皮、酿皮，是中国西部以及中国北方众多地区的小吃，起源于陕西关中地区，被许多人认为是陕西小吃中最受欢迎的品种。 凉皮据说源于秦始皇时期，距今已有两千多年历史。也有說法是从唐代“冷淘麵”演变而来，以“白、薄、光、软、酿、香”而闻名。凉皮一年四季都可以吃到，因为“凉”，所以在夏天吃的人更多。 凉皮因原料、制作方法、地域不同，有热米（面）皮、擀面皮、烙面皮、酿皮等。口味有麻辣，酸甜，香辣等各种口味。从制作方法上可大体分为：蒸麵皮、擀麵皮和烙麵皮。蒸麵皮的主要制作方法是由面粉（将面筋洗出）或米粉加水均匀搅拌製成糊状，盛入圆形平底的金属容器，摇摆凉皮容器使麵/米糊平展得铺在容器底，然后放入开水锅或蒸笼内蒸製（蒸熟后的圆形整张皮子大约0.5厘米厚，直径近1米）。随后把凉皮过凉水冷却，用近1米长、20余厘米宽的大铡刀切成宽0.5厘米至2厘米的长条（根据製作材料不同，颜色有稍许不同），调拌时可根据不同风味加入盐、醋、芝麻酱、辣椒油、麵筋、黄瓜丝、豆芽、蒜汁和时令蔬菜等。 現在凉皮是北京等大城市的街头快餐之一。",
    "metadata": {
      "cuisine_type": "西北菜 （陕西，甘肃等地）",
      "dish_name": "酿皮",
      "english_name": "酿皮",
      "source": "wikipedia",
      "source_url": "https://zh.wikipedia.org/wiki/%E5%87%89%E7%9A%AE",
      "timestamp": "2024-11-24T13:28:34.452956"
    }
  },
  {
    "id": "recipe_20241124_132835",
    "content": "Title: 糖醋鲤鱼\nChinese Name: 糖醋丸子\nEnglish Name: 糖醋丸子\nCuisine Type: 西北菜 （陕西，甘肃等地）\n\n糖醋鲤鱼，为一道中国名菜，为鲁菜济南派系的代表菜之一。 主要用料为鲤鱼，其中尤以黄河鲤鱼为最佳。调料有白糖、醋等。基本做菜流程为：首先要将鲤鱼炸熟，然后再将糖醋汁浇于鱼体之上，并达到“外焦里嫩”的效果即可完成菜品的制作。正宗糖醋汁不用番茄酱调味，但是因为番茄酱颜色鲜艳而且酸甜得度，所以在民间很受欢迎。",
    "metadata": {
      "cuisine_type": "西北菜 （陕西，甘肃等地）",
      "dish_name": "糖醋丸子",
      "english_name": "糖醋丸子",
      "source": "wikipedia",
      "source_url": "https://zh.wikipedia.org/wiki/%E7%B3%96%E9%86%8B%E9%B2%A4%E9%B1%BC",
      "timestamp": "2024-11-24T13:28:35.985134"
    }
  },
  {
    "id": "recipe_20241124_132837",
    "content": "Title: 酱牛肉\nChinese Name: 酱牛肉\nEnglish Name: 酱牛肉\nCuisine Type: 西北菜 （陕西，甘肃等地）\n\n酱牛肉是一道牛肉食品，制作方法比較简单。一般被认为是属于清真食品，在中国北方尤其受到欢迎。事实上，酱牛肉在中国已经有上千年的历史，远远早于伊斯兰教的诞生。具体出处由于年代久远，已经不可细考。 在《楚辞》的“大招”和“招魂”篇里的菜谱上都有牛肉的菜谱。在宋朝之前，中国的主要肉食就包括牛羊肉。",
    "metadata": {
      "cuisine_type": "西北菜 （陕西，甘肃等地）",
      "dish_name": "酱牛肉",
      "english_name": "酱牛肉",
      "source": "wikipedia",
      "source_url": "https://zh.wikipedia.org/wiki/%E9%85%B1%E7%89%9B%E8%82%89",
      "timestamp": "2024-11-24T13:28:37.687596"
    }
  },
  {
    "id": "recipe_20241124_132839",
    "content": "Title: 抓饭\nChinese Name: 手抓羊肉\nEnglish Name: 手抓羊肉\nCuisine Type: 西北菜 （陕西，甘肃等地）\n\n抓饭，也叫香料饭，是西亞、中亞、南亚等地的传统食物，也是中亚族群的标志性食物。不同地方的手抓飯有不同的風味，除了用料不同外，佐料也是主要原因。常見的特徵包括用湯來煮米飯（或其他穀物）、加入香料、肉、蔬菜和果乾，並追求讓米粒分開而不是黏在一起。",
    "metadata": {
      "cuisine_type": "西北菜 （陕西，甘肃等地）",
      "dish_name": "手抓羊肉",
      "english_name": "手抓羊肉",
      "source": "wikipedia",
      "source_url": "https://zh.wikipedia.org/wiki/%E6%8A%93%E9%A5%AD",
      "timestamp": "2024-11-24T13:28:39.187407"
    }
  },
  {
    "id": "recipe_20241124_132840",
    "content": "Title: 皮冻\nChinese Name: 猪皮冻\nEnglish Name: 猪皮冻\nCuisine Type: 西北菜 （陕西，甘肃等地）\n\n皮冻是一种用猪皮原材料制成的凝胶状食品，通常作为凉菜出现。",
    "metadata": {
      "cuisine_type": "西北菜 （陕西，甘肃等地）",
      "dish_name": "猪皮冻",
      "english_name": "猪皮冻",
      "source": "wikipedia",
      "source_url": "https://zh.wikipedia.org/wiki/%E7%9A%AE%E5%86%BB",
      "timestamp": "2024-11-24T13:28:40.700302"
    }
  },
  {
    "id": "recipe_20241124_132842",
    "content": "Title: 凉皮\nChinese Name: 面皮/凉皮\nEnglish Name: 面皮/凉皮\nCuisine Type: 西北菜 （陕西，甘肃等地）\n\n凉皮又称皮子、酿皮子、麵皮、擀面皮、米皮、酿皮，是中国西部以及中国北方众多地区的小吃，起源于陕西关中地区，被许多人认为是陕西小吃中最受欢迎的品种。 凉皮据说源于秦始皇时期，距今已有两千多年历史。也有說法是从唐代“冷淘麵”演变而来，以“白、薄、光、软、酿、香”而闻名。凉皮一年四季都可以吃到，因为“凉”，所以在夏天吃的人更多。 凉皮因原料、制作方法、地域不同，有热米（面）皮、擀面皮、烙面皮、酿皮等。口味有麻辣，酸甜，香辣等各种口味。从制作方法上可大体分为：蒸麵皮、擀麵皮和烙麵皮。蒸麵皮的主要制作方法是由面粉（将面筋洗出）或米粉加水均匀搅拌製成糊状，盛入圆形平底的金属容器，摇摆凉皮容器使麵/米糊平展得铺在容器底，然后放入开水锅或蒸笼内蒸製（蒸熟后的圆形整张皮子大约0.5厘米厚，直径近1米）。随后把凉皮过凉水冷却，用近1米长、20余厘米宽的大铡刀切成宽0.5厘米至2厘米的长条（根据製作材料不同，颜色有稍许不同），调拌时可根据不同风味加入盐、醋、芝麻酱、辣椒油、麵筋、黄瓜丝、豆芽、蒜汁和时令蔬菜等。 現在凉皮是北京等大城市的街头快餐之一。",
    "metadata": {
      "cuisine_type": "西北菜 （陕西，甘肃等地）",
      "dish_name": "面皮/凉皮",
      "english_name": "面皮/凉皮",
      "source": "wikipedia",
      "source_url": "https://zh.wikipedia.org/wiki/%E5%87%89%E7%9A%AE",
      "timestamp": "2024-11-24T13:28:42.402053"
    }
  },
  {
    "id": "recipe_20241124_132843",
    "content": "Title: 酸汤鱼\nChinese Name: 凯里酸汤鱼\nEnglish Name: 凯里酸汤鱼\nCuisine Type: 黔菜 (贵州）\n\n酸汤鱼是中国贵州省的代表性菜品，源自黔东南苗族侗族自治州的苗族美食，距今酸汤鱼至少有数百年历史。酸汤鱼常见于苗族的婚礼、婴儿满月、聚餐、招待贵客等。其酸汤的原料可使用糯米粉发酵配以贵州地产的樱桃番茄熬制而成，并将酸汤汁与鲤鱼、草鱼或黑鱼煮制并配以辣椒、花椒、盐等调料即可成菜。酸汤鱼以其鱼肉细嫩，酸香味鲜而受人欢迎。此外，亦有将番茄腌制后形成的酸汤作为其中酸汤的原料，并配以鲤鱼、黄豆芽、笋、豆腐等煮制而成，并辅之腐乳、香菜、辣椒为蘸料的做法。 2017年，贵州省商务厅、贵阳市人民政府等主办的贵州黔菜品牌系列活动十大名菜比赛中，将苗家酸汤鱼列为贵州黔菜十大名菜。",
    "metadata": {
      "cuisine_type": "黔菜 (贵州）",
      "dish_name": "凯里酸汤鱼",
      "english_name": "凯里酸汤鱼",
      "source": "wikipedia",
      "source_url": "https://zh.wikipedia.org/wiki/%E9%85%B8%E6%B1%A4%E9%B1%BC",
      "timestamp": "2024-11-24T13:28:43.891619"
    }
  },
  {
    "id": "recipe_20241124_132845",
    "content": "Title: 青岩镇\nChinese Name: 豆腐圆子\nEnglish Name: 豆腐圆子\nCuisine Type: 黔菜 (贵州）\n\n青岩镇，又称青岩古镇，是中华人民共和国贵州省貴陽市花溪区下辖的一个乡镇级行政单位。 青岩古镇，贵州四大古镇之一，位于贵阳市南郊，建于明洪武十年（1378年），原为军事要塞 。古镇内设计精巧、工艺精湛的明清古建筑交错密布，寺庙、 楼阁画栋雕梁、飞角重檐相间。镇人文荟萃，有历史名人周渔璜、清末状元赵以炯（贵州历史上第一个文状元）。镇内有近代史上震惊中外的青岩教案遗址、赵状元府第、平刚先生故居、红军长征作战指挥部等历史文物。周恩来的父亲、邓颖超的母亲、李克农等革命前辈及其家属均在青岩秘密居住过。青岩古镇还是抗战期间浙江大学的西迁办学点之一。 2005年9月青岩古镇景区被建设部、国家文物局公布为第二批中国历史文化名镇。2013年在顶峰国际非物质文化遗产保护与传承旅游规划项目中被誉为中国最具魅力小镇之一。",
    "metadata": {
      "cuisine_type": "黔菜 (贵州）",
      "dish_name": "豆腐圆子",
      "english_name": "豆腐圆子",
      "source": "wikipedia",
      "source_url": "https://zh.wikipedia.org/wiki/%E9%9D%92%E5%B2%A9%E9%95%87",
      "timestamp": "2024-11-24T13:28:45.421879"
    }
  },
  {
    "id": "recipe_20241124_132847",
    "content": "Title: 酱汁肉\nChinese Name: 荷叶粉蒸肉\nEnglish Name: 荷叶粉蒸肉\nCuisine Type: 黔菜 (贵州）\n\n酱汁肉，又名酒焖汁肉，是江苏苏州的地方特色卤菜，有300余年的历史。每年春季供应，与荷叶粉蒸肉、扣肉、酱方并称为“苏州一年里的四块肉”。 酱汁肉采用猪五花肋条肉，切为大块，洗净焯水后，用老卤烧制三小时余，其间还要添加红曲米及白糖，以形成红艳色泽。成品具有酥而不烂、入口即化的特点。在苏州，酱汁肉以老字号陆稿荐所制最为知名。",
    "metadata": {
      "cuisine_type": "黔菜 (贵州）",
      "dish_name": "荷叶粉蒸肉",
      "english_name": "荷叶粉蒸肉",
      "source": "wikipedia",
      "source_url": "https://zh.wikipedia.org/wiki/%E9%85%B1%E6%B1%81%E8%82%89",
      "timestamp": "2024-11-24T13:28:47.073496"
    }
  },
  {
    "id": "recipe_20241124_132848",
    "content": "Title: 六盘水市\nChinese Name: 水城烙锅\nEnglish Name: 水城烙锅\nCuisine Type: 黔菜 (贵州）\n\n六盘水市是中华人民共和国贵州省下辖的地级市，位于贵州省西部。市境东接安顺市，南连黔西南州，西界云南省曲靖市，北邻毕节市。地处滇黔两省结合部乌蒙山区，长江、珠江上游分水岭，南盘江、北盘江流域两岸，矿产资源十分丰富。全市总面积9,965平方公里，人口340万，市人民政府驻钟山区。六盘水市因气候宜人而有“中国凉都”的称号。",
    "metadata": {
      "cuisine_type": "黔菜 (贵州）",
      "dish_name": "水城烙锅",
      "english_name": "水城烙锅",
      "source": "wikipedia",
      "source_url": "https://zh.wikipedia.org/wiki/%E5%85%AD%E7%9B%98%E6%B0%B4%E5%B8%82",
      "timestamp": "2024-11-24T13:28:48.569469"
    }
  },
  {
    "id": "recipe_20241124_132850",
    "content": "Title: 辣子鸡\nChinese Name: 辣子鸡\nEnglish Name: 辣子鸡\nCuisine Type: 黔菜 (贵州）\n\n辣子鸡，又名辣子鸡丁，起源于重庆，所以也称重庆辣子鸡或歌乐山辣子鸡，是下河帮川菜的辣子系列代表。",
    "metadata": {
      "cuisine_type": "黔菜 (贵州）",
      "dish_name": "辣子鸡",
      "english_name": "辣子鸡",
      "source": "wikipedia",
      "source_url": "https://zh.wikipedia.org/wiki/%E8%BE%A3%E5%AD%90%E9%B8%A1",
      "timestamp": "2024-11-24T13:28:50.044214"
    }
  },
  {
    "id": "recipe_20241124_132851",
    "content": "Title: 絲娃娃\nChinese Name: 丝娃娃\nEnglish Name: 丝娃娃\nCuisine Type: 黔菜 (贵州）\n\n絲娃娃，是一種貴州貴陽的特色小吃，接近其他地方的春卷或裹卷，但麵皮較小，吃法不同。",
    "metadata": {
      "cuisine_type": "黔菜 (贵州）",
      "dish_name": "丝娃娃",
      "english_name": "丝娃娃",
      "source": "wikipedia",
      "source_url": "https://zh.wikipedia.org/wiki/%E7%B5%B2%E5%A8%83%E5%A8%83",
      "timestamp": "2024-11-24T13:28:51.692397"
    }
  },
  {
    "id": "recipe_20241124_132853",
    "content": "Title: 紅燒肉\nChinese Name: 毛式红烧肉\nEnglish Name: 毛式红烧肉\nCuisine Type: 苏菜（江苏）\n\n紅燒肉，是指通常以豬肉與醬油為主原料製做而來的一種華人家常食品，也可用其他哺乳動物的肉體來做主原料，為歷史悠久的傳統名菜，起源時間難以追溯。其樣式與製作方法多變，并無統一烹調配方。中國幾乎每個地方與飯店都有其獨特的樣式風格，配料多樣，傳統的樣式肥肉多於瘦肉。紅燒肉冬天食用可以抗寒，蛋白質含量很高，但同时飽和脂肪的含量也较高，患有代謝症候群則不宜多食。有一些知名菜式如東坡肉等，現時很多泡麵以紅燒口味作為招攬。",
    "metadata": {
      "cuisine_type": "苏菜（江苏）",
      "dish_name": "毛式红烧肉",
      "english_name": "毛式红烧肉",
      "source": "wikipedia",
      "source_url": "https://zh.wikipedia.org/wiki/%E7%B4%85%E7%87%92%E8%82%89",
      "timestamp": "2024-11-24T13:28:53.193571"
    }
  },
  {
    "id": "recipe_20241124_132854",
    "content": "Title: 盐水鸭\nChinese Name: 盐水鸭\nEnglish Name: 盐水鸭\nCuisine Type: 苏菜（江苏）\n\n盐水鸭属京苏菜，是中国南京特产的一种传统卤菜鸭馔，是一种低温肉制品。盐水鸭口味清淡而略带咸味，肥而不腻、鲜嫩味美。盐水鸭一年四季都可以制作，以农历八月间桂花盛开时制作的为上，因为传说这一季节的盐水鸭肉中有桂花香味，因此又名“桂花鸭”。盐水鸭的传统加工工艺是江苏省非物质文化遗产推荐项目。盐水鸭也在重庆等地流行。",
    "metadata": {
      "cuisine_type": "苏菜（江苏）",
      "dish_name": "盐水鸭",
      "english_name": "盐水鸭",
      "source": "wikipedia",
      "source_url": "https://zh.wikipedia.org/wiki/%E7%9B%90%E6%B0%B4%E9%B8%AD",
      "timestamp": "2024-11-24T13:28:54.682862"
    }
  },
  {
    "id": "recipe_20241124_132856",
    "content": "Title: 小籠包\nChinese Name: 无锡小笼包\nEnglish Name: 无锡小笼包\nCuisine Type: 苏菜（江苏）\n\n小籠包是一种诞生于中国江南地区的著名点心，吴语太湖片又称小籠饅頭，多處地方亦盛行，例如廣東、香港、台灣，以“体小、馅大、汁多、味鲜、皮薄、形美”而著称。 汤包源于北宋京城开封的灌汤包，特色的餡料經過蒸煮化為汁水，现代形式的小笼包起源于江南，如今小笼包是常州、无锡、苏州、南京、上海、杭州、宁波、嘉兴等地的传统小吃。后又在各地得到发展和演变，形成不同的口味。 清代道光年间出现了现代形式的小笼包，并在各地都形成了各自的特色，如喝起來講究以常州味鲜、南京味清、无锡味甜，但都具有湯汁多、皮薄卤足、鲜香與美味等共同特点，并在开封、天津等地也得到了传扬。",
    "metadata": {
      "cuisine_type": "苏菜（江苏）",
      "dish_name": "无锡小笼包",
      "english_name": "无锡小笼包",
      "source": "wikipedia",
      "source_url": "https://zh.wikipedia.org/wiki/%E5%B0%8F%E7%B1%A0%E5%8C%85",
      "timestamp": "2024-11-24T13:28:56.211469"
    }
  },
  {
    "id": "recipe_20241124_132857",
    "content": "Title: 松鼠鳜鱼\nChinese Name: 松鼠鱼\nEnglish Name: 松鼠鱼\nCuisine Type: 苏菜（江苏）\n\n松鼠鱖（guì）鱼，也可寫成松鼠桂魚、松子桂魚，是一道源自中国江苏苏州的番茄汁油炸魚的菜餚。 以鳜鱼为原料，经去骨、剖花、炸製，呈松鼠状，再浇上糖醋汁而成。该菜式口味鲜甜、口感脆嫩。現在蘇州以外地方亦用黃花魚代替鱖魚，稱為松鼠黃魚。",
    "metadata": {
      "cuisine_type": "苏菜（江苏）",
      "dish_name": "松鼠鱼",
      "english_name": "松鼠鱼",
      "source": "wikipedia",
      "source_url": "https://zh.wikipedia.org/wiki/%E6%9D%BE%E9%BC%A0%E9%B3%9C%E9%B1%BC",
      "timestamp": "2024-11-24T13:28:57.917065"
    }
  },
  {
    "id": "recipe_20241124_132859",
    "content": "Title: 青糰\nChinese Name: 青团\nEnglish Name: 青团\nCuisine Type: 苏菜（江苏）\n\n青团，閩南、潮汕稱為草仔粿，客家人稱為青粄，香港稱為清明仔或雞屎藤茶粿，是中國南方部分地区與台灣清明節、寒食節、中元節的米食之一，因為其外皮中使用了青草汁液，故色澤為青綠色，所以叫做青糰。傳統為甜鹹兩種口味，一種包棗泥、豆沙等，另一種包豬肉、竹筍等；現代出現印上卡通圖案或者添加一些夾心軟糖。口味有巧克力味、各種水果味，甚至燕窩味等等，餡料出現猪油筍子、金针鲜肉、金華火腿、雞湯鮑魚等口味。有些甚至包著冰淇淋，或是變成西餐後的甜點。",
    "metadata": {
      "cuisine_type": "苏菜（江苏）",
      "dish_name": "青团",
      "english_name": "青团",
      "source": "wikipedia",
      "source_url": "https://zh.wikipedia.org/wiki/%E9%9D%92%E7%B3%B0",
      "timestamp": "2024-11-24T13:28:59.459525"
    }
  },
  {
    "id": "recipe_20241124_132900",
    "content": "Title: 太湖三白\nChinese Name: 太湖银鱼\nEnglish Name: 太湖银鱼\nCuisine Type: 苏菜（江苏）\n\n太湖三白是指中国太湖的三种河鲜类特产——白鱼、银鱼和白虾，是江苏省常州市武进区（原武进县）、苏州市吴中区（原吴县）和无锡市地方系列菜“太湖船菜”的招牌食材，由于其色泽均呈白色，因而称为“太湖三白”。利用太湖三白所制作之菜肴的选料，极为注重食材的新鲜程度；尤因其出水即易死亡，故而最适合在水边或船上烹制太湖三白。以太湖三白制作菜肴之方法，多为清蒸白灼等。",
    "metadata": {
      "cuisine_type": "苏菜（江苏）",
      "dish_name": "太湖银鱼",
      "english_name": "太湖银鱼",
      "source": "wikipedia",
      "source_url": "https://zh.wikipedia.org/wiki/%E5%A4%AA%E6%B9%96%E4%B8%89%E7%99%BD",
      "timestamp": "2024-11-24T13:29:00.958267"
    }
  },
  {
    "id": "recipe_20241124_132902",
    "content": "Title: 响油鳝糊\nChinese Name: 响油鳝糊\nEnglish Name: 响油鳝糊\nCuisine Type: 苏菜（江苏）\n\n响油鳝糊是中国苏帮菜中无锡菜以及上海本幫菜的传统菜式。以中小型鳝鱼烫杀后划出的鳝丝为主料，辅料可以添加金华火腿、冬笋等，调料包括绍酒、姜、葱、老抽、生抽、糖、白胡椒粉、生粉等。急火爆炒，用水淀粉勾芡后趁热浇上热油，上桌时会发出“嘶嘶”的声音，故名“响油鳝糊”。该菜式色泽油亮，口感甜咸。",
    "metadata": {
      "cuisine_type": "苏菜（江苏）",
      "dish_name": "响油鳝糊",
      "english_name": "响油鳝糊",
      "source": "wikipedia",
      "source_url": "https://zh.wikipedia.org/wiki/%E5%93%8D%E6%B2%B9%E9%B3%9D%E7%B3%8A",
      "timestamp": "2024-11-24T13:29:02.775678"
    }
  },
  {
    "id": "recipe_20241124_132904",
    "content": "Title: 陽春麵\nChinese Name: 阳春面\nEnglish Name: 阳春面\nCuisine Type: 苏菜（江苏）\n\n陽春麵，又稱光麵或清湯麵、白湯麵和上海麵，是指一種幾乎不加上任何配菜的湯麵或乾麵，常見於台灣與江苏、上海。便宜簡便是受歡迎的主因，煮法沒有規限，細如龍鬚麵或者粗如寬麵均可使用，通常僅以豬油、醬油調味。 「陽春」一詞的由來，據《辞海》釋：「農曆十月為小陽春，市井隱語逐以陽春代表十。」明人所著《五雜俎‧天》中云：「即天地之光，四月多寒，而十月多暖，有桃李生華者，俗謂之小陽春。」據此可見，農曆十月的別稱為小陽春，故又更進一步地引申陽春為十數之意。而陽春麵剛上市之時，價格正好是十分錢一碗，好事者遂將這十分錢一碗的光麵冠以陽春麵美名，取其十分錢與農曆十月皆為十數之故。 另一種使用餃子代替麵條再加上蝦米皮的料理稱為陽春湯餃。",
    "metadata": {
      "cuisine_type": "苏菜（江苏）",
      "dish_name": "阳春面",
      "english_name": "阳春面",
      "source": "wikipedia",
      "source_url": "https://zh.wikipedia.org/wiki/%E9%99%BD%E6%98%A5%E9%BA%B5",
      "timestamp": "2024-11-24T13:29:04.271289"
    }
  },
  {
    "id": "recipe_20241124_132905",
    "content": "Title: 蟹黄汤包\nChinese Name: 蟹黄汤包\nEnglish Name: 蟹黄汤包\nCuisine Type: 苏菜（江苏）\n\n蟹黄汤包为江苏传统美食，明、清时期已经享有盛誉。其特色是皮薄如纸，以制作“绝”、形态“美”、吃法“奇”出名。 蟹黄汤包的制作原料為螃蟹的蟹黄和蟹肉，汤为原味鸡汤。 其中龙袍蟹黄汤包和靖江蟹黄汤包較爲出名，南京六合区常年举办龙袍蟹黄汤包节，此外扬州等地的汤包也非常有名。",
    "metadata": {
      "cuisine_type": "苏菜（江苏）",
      "dish_name": "蟹黄汤包",
      "english_name": "蟹黄汤包",
      "source": "wikipedia",
      "source_url": "https://zh.wikipedia.org/wiki/%E8%9F%B9%E9%BB%84%E6%B1%A4%E5%8C%85",
      "timestamp": "2024-11-24T13:29:05.767077"
    }
  },
  {
    "id": "recipe_20241124_132907",
    "content": "Title: 腸粉\nChinese Name: 鸡蛋肠粉\nEnglish Name: 鸡蛋肠粉\nCuisine Type: 粤菜（广东等地）\n\n腸粉，是一种使用米漿及澄麵製成的透明、捲狀的食物，口感柔嫩有彈性，在香港和广东非常有名，其後也流傳到其他地方。 腸粉種類繁多，例如以布拉成的稱為布拉腸粉，沒有布拉的稱手拉腸粉。石磨腸粉則是將用石磨製作的米漿淋到托盤上，再放入抽屜式蒸架。 腸粉傳統以碎牛肉、魚片、鮮蝦仁或廣東叉燒為餡料，也是廣東和香港茶樓常見的點心，常見的有鮮蝦腸粉、牛肉腸粉、叉燒腸粉。而不加餡、沒有灑上小蝦米和蔥的則稱齋腸（又稱豬腸粉），是傳統粥店中早餐常見的食品。",
    "metadata": {
      "cuisine_type": "粤菜（广东等地）",
      "dish_name": "鸡蛋肠粉",
      "english_name": "鸡蛋肠粉",
      "source": "wikipedia",
      "source_url": "https://zh.wikipedia.org/wiki/%E8%85%B8%E7%B2%89",
      "timestamp": "2024-11-24T13:29:07.459100"
    }
  },
  {
    "id": "recipe_20241124_132908",
    "content": "Title: 腸粉\nChinese Name: 红米肠粉\nEnglish Name: 红米肠粉\nCuisine Type: 粤菜（广东等地）\n\n腸粉，是一种使用米漿及澄麵製成的透明、捲狀的食物，口感柔嫩有彈性，在香港和广东非常有名，其後也流傳到其他地方。 腸粉種類繁多，例如以布拉成的稱為布拉腸粉，沒有布拉的稱手拉腸粉。石磨腸粉則是將用石磨製作的米漿淋到托盤上，再放入抽屜式蒸架。 腸粉傳統以碎牛肉、魚片、鮮蝦仁或廣東叉燒為餡料，也是廣東和香港茶樓常見的點心，常見的有鮮蝦腸粉、牛肉腸粉、叉燒腸粉。而不加餡、沒有灑上小蝦米和蔥的則稱齋腸（又稱豬腸粉），是傳統粥店中早餐常見的食品。",
    "metadata": {
      "cuisine_type": "粤菜（广东等地）",
      "dish_name": "红米肠粉",
      "english_name": "红米肠粉",
      "source": "wikipedia",
      "source_url": "https://zh.wikipedia.org/wiki/%E8%85%B8%E7%B2%89",
      "timestamp": "2024-11-24T13:29:08.943350"
    }
  },
  {
    "id": "recipe_20241124_132910",
    "content": "Title: 叉燒包\nChinese Name: 叉烧包\nEnglish Name: 叉烧包\nCuisine Type: 粤菜（广东等地）\n\n叉燒包是香港、澳門以至廣東具代表性的粤式點心之一。以切成小塊的叉燒，加入蠔油等調味成為餡料，外面以麪粉包裹，放在蒸籠內蒸熟而成。叉燒包一般大小為直徑5公分（1.97英吋）左右，一籠通常為三或四個。好的叉燒包採用肥瘦適中的叉燒作餡，包皮蒸熟後軟滑剛好，稍為裂開露出叉燒餡料，滲發出陣陣叉燒的香味。又有一說傳統叉燒包的標準要求是「高身雀籠型，大肚收篤，爆口而僅微微露餡」。在夏威夷，叉烧包被称作Manapua，是夏威夷语mea ʻono puaʻa（意为“美味的猪肉食品”）的缩写，在美屬薩摩亞则被称为Keke pua'a。香港另外還有「雪影叉燒包」及「雪山叉燒包」的版本，將原本的蒸制改為烘烤而成。",
    "metadata": {
      "cuisine_type": "粤菜（广东等地）",
      "dish_name": "叉烧包",
      "english_name": "叉烧包",
      "source": "wikipedia",
      "source_url": "https://zh.wikipedia.org/wiki/%E5%8F%89%E7%87%92%E5%8C%85",
      "timestamp": "2024-11-24T13:29:10.448951"
    }
  },
  {
    "id": "recipe_20241124_132912",
    "content": "Title: 牛仔骨\nChinese Name: 黑椒牛仔骨\nEnglish Name: 黑椒牛仔骨\nCuisine Type: 粤菜（广东等地）\n\n牛仔骨（英語：Short ribs），又稱牛小排，是一种人類食品，由牛的肋骨连肉切块而成，通常会进行烧烤或者煎熟并配黑椒汁一起吃。",
    "metadata": {
      "cuisine_type": "粤菜（广东等地）",
      "dish_name": "黑椒牛仔骨",
      "english_name": "黑椒牛仔骨",
      "source": "wikipedia",
      "source_url": "https://zh.wikipedia.org/wiki/%E7%89%9B%E4%BB%94%E9%AA%A8",
      "timestamp": "2024-11-24T13:29:12.232453"
    }
  },
  {
    "id": "recipe_20241124_132913",
    "content": "Title: 蝦餃\nChinese Name: 虾饺\nEnglish Name: 虾饺\nCuisine Type: 粤菜（广东等地）\n\n蝦餃，又稱水晶蝦餃，在廣東省以外的地區又可稱為港式蒸餃、廣式蒸餃，是一種以透明澄麵皮包裹一至兩隻蝦的蒸餃菜，份量大小多以一口為限。 常见的蝦餃是半月形、表面似蜘蛛肚的，約有十三褶。传统广式西关蝦饺餡料有河蝦、肥豬肉、韭黄，而且必须是十三褶半，港式多简化要求，改为海蝦、笋及半肥瘦猪肉，褶数由九至十三褶不等，当中世有些标称有些不計較成本讓人覺得超值的是純龙蝦肉、鹅肝醤的蝦餃。優質美味的蝦餃一定要皮薄而軟，如果餃皮必须是有弹性兼半透明；蝦肉要爽口彈牙，餃內有少量汁液，全隻餃則要夠熱為最佳。",
    "metadata": {
      "cuisine_type": "粤菜（广东等地）",
      "dish_name": "虾饺",
      "english_name": "虾饺",
      "source": "wikipedia",
      "source_url": "https://zh.wikipedia.org/wiki/%E8%9D%A6%E9%A4%83",
      "timestamp": "2024-11-24T13:29:13.733144"
    }
  },
  {
    "id": "recipe_20241124_132915",
    "content": "Title: 鍋飯\nChinese Name: 煲仔饭\nEnglish Name: 煲仔饭\nCuisine Type: 粤菜（广东等地）\n\n鍋飯，廣東地區稱為煲仔飯，又有砂鍋飯、瓦鍋飯等名稱，日語稱為稱為土锅饭（日语：土鍋飯／どなべめし）。是以砂鍋或金屬鍋盛載著飯和食材用炭火慢慢地燒熟的食品，過去通常在冬季食用，現在一年四季人們均可享用到。",
    "metadata": {
      "cuisine_type": "粤菜（广东等地）",
      "dish_name": "煲仔饭",
      "english_name": "煲仔饭",
      "source": "wikipedia",
      "source_url": "https://zh.wikipedia.org/wiki/%E9%8D%8B%E9%A3%AF",
      "timestamp": "2024-11-24T13:29:15.683093"
    }
  },
  {
    "id": "recipe_20241124_132917",
    "content": "Title: 牛肉面\nChinese Name: 咖喱牛腩牛筋面\nEnglish Name: 咖喱牛腩牛筋面\nCuisine Type: 粤菜（广东等地）\n\n牛肉麵是泛指各種以燉煮過的牛肉為主要配料之湯麵食，其根源難以追溯，但與近代牛肉麵調理方式較為接近的麵食，清燉類的牛肉麵部分認為起源於兰州牛肉面，原本是陈维精所创。據學者說法，紅燒風味牛肉麵根源始于山东鲁菜烹饪技法，衍生出的台灣牛肉麵则起源於台灣高雄市岡山區空軍眷村。現今牛肉麵已是華人的普遍食物，各地方的牛肉麵都有其特色。現在有不少泡麵都是以添加牛肉或牛肉口味而成牛肉麵，尤其是在台灣非常的普遍。",
    "metadata": {
      "cuisine_type": "粤菜（广东等地）",
      "dish_name": "咖喱牛腩牛筋面",
      "english_name": "咖喱牛腩牛筋面",
      "source": "wikipedia",
      "source_url": "https://zh.wikipedia.org/wiki/%E7%89%9B%E8%82%89%E9%9D%A2",
      "timestamp": "2024-11-24T13:29:17.339395"
    }
  },
  {
    "id": "recipe_20241124_132918",
    "content": "Title: 鱼丸\nChinese Name: 鱼丸粉\nEnglish Name: 鱼丸粉\nCuisine Type: 粤菜（广东等地）\n\n鱼丸，又稱魚肉丸子，是水鄉人家常見的小吃食品，用魚肉加澱粉製成，多數為球形，但亦有其他形狀，如腰豆形，正立方體等。在香港、澳門和廣東稱之為魚蛋。",
    "metadata": {
      "cuisine_type": "粤菜（广东等地）",
      "dish_name": "鱼丸粉",
      "english_name": "鱼丸粉",
      "source": "wikipedia",
      "source_url": "https://zh.wikipedia.org/wiki/%E9%B1%BC%E4%B8%B8",
      "timestamp": "2024-11-24T13:29:18.854419"
    }
  },
  {
    "id": "recipe_20241124_132920",
    "content": "Title: 燒鵝\nChinese Name: 脆皮烧鹅\nEnglish Name: 脆皮烧鹅\nCuisine Type: 粤菜（广东等地）\n\n烧鹅，是燒味的一種。是把塗满调味料的鹅，挂进特製的炭炉裏用木炭高温烧烤出来的食物，以皮脆有光澤，肉汁多而不帶腥味為上品，通常配以酸梅醬食用。在广东是非常常见的菜品。",
    "metadata": {
      "cuisine_type": "粤菜（广东等地）",
      "dish_name": "脆皮烧鹅",
      "english_name": "脆皮烧鹅",
      "source": "wikipedia",
      "source_url": "https://zh.wikipedia.org/wiki/%E7%87%92%E9%B5%9D",
      "timestamp": "2024-11-24T13:29:20.318292"
    }
  },
  {
    "id": "recipe_20241124_132921",
    "content": "Title: 鳃棘鲈\nChinese Name: 清蒸鲈鱼\nEnglish Name: 清蒸鲈鱼\nCuisine Type: 粤菜（广东等地）\n\n鳃棘鲈（学名：Plectropomus leopardus）为鮨科鳃棘鲈属的鱼类，俗名：豹紋鰓棘鱸、花斑刺鳃鮨、豹纹豹脍、東星斑、七星斑。分布于印度洋到太平洋中部、北至日本南部的菲律宾、台湾岛以及南海诸岛的海南岛等，属于暖水性沿岸鱼类。其一般生活于珊瑚礁。",
    "metadata": {
      "cuisine_type": "粤菜（广东等地）",
      "dish_name": "清蒸鲈鱼",
      "english_name": "清蒸鲈鱼",
      "source": "wikipedia",
      "source_url": "https://zh.wikipedia.org/wiki/%E9%B3%83%E6%A3%98%E9%B2%88",
      "timestamp": "2024-11-24T13:29:21.969837"
    }
  },
  {
    "id": "recipe_20241124_132923",
    "content": "Title: 乾炒牛河\nChinese Name: 干炒牛河\nEnglish Name: 干炒牛河\nCuisine Type: 粤菜（广东等地）\n\n乾炒牛河，或名牛肉炒河粉，是粤菜的一道菜色，也是香港飲食文化的一部分，以芽菜、河粉、牛肉等炒成。在香港以至海外的港式酒家、茶餐廳，乾炒牛河幾乎成為必備菜色。",
    "metadata": {
      "cuisine_type": "粤菜（广东等地）",
      "dish_name": "干炒牛河",
      "english_name": "干炒牛河",
      "source": "wikipedia",
      "source_url": "https://zh.wikipedia.org/wiki/%E4%B9%BE%E7%82%92%E7%89%9B%E6%B2%B3",
      "timestamp": "2024-11-24T13:29:23.483142"
    }
  },
  {
    "id": "recipe_20241124_132925",
    "content": "Title: 牛肉丸\nChinese Name: 陈皮牛肉丸\nEnglish Name: 陈皮牛肉丸\nCuisine Type: 粤菜（广东等地）\n\n牛肉丸，亦称潮汕手打牛丸，是客家與潮州的特色小吃，為使用牛肉所做成的肉丸，由於香港及珠三角地区有相當的祖籍潮汕地區的居民，故牛肉丸亦在这一带流行。",
    "metadata": {
      "cuisine_type": "粤菜（广东等地）",
      "dish_name": "陈皮牛肉丸",
      "english_name": "陈皮牛肉丸",
      "source": "wikipedia",
      "source_url": "https://zh.wikipedia.org/wiki/%E7%89%9B%E8%82%89%E4%B8%B8",
      "timestamp": "2024-11-24T13:29:25.016165"
    }
  },
  {
    "id": "recipe_20241124_132926",
    "content": "Title: 臭鱖魚\nChinese Name: 臭鳜鱼\nEnglish Name: 臭鳜鱼\nCuisine Type: 徽菜 （安徽）\n\n臭鳜鱼，又名腌鲜鳜鱼，是安徽省黄山市一带的特色菜餚，用鱖魚製成，也是徽菜的代表之一。",
    "metadata": {
      "cuisine_type": "徽菜 （安徽）",
      "dish_name": "臭鳜鱼",
      "english_name": "臭鳜鱼",
      "source": "wikipedia",
      "source_url": "https://zh.wikipedia.org/wiki/%E8%87%AD%E9%B1%96%E9%AD%9A",
      "timestamp": "2024-11-24T13:29:26.532364"
    }
  },
  {
    "id": "recipe_20241124_132928",
    "content": "Title: 猪血丸子\nChinese Name: 猪血丸子\nEnglish Name: 猪血丸子\nCuisine Type: 湘菜（湖南）\n\n猪血丸子，或作猪血圆子，是中国湖南邵阳的传统特色家常菜，以其独特的制作工艺和风味著称。",
    "metadata": {
      "cuisine_type": "湘菜（湖南）",
      "dish_name": "猪血丸子",
      "english_name": "猪血丸子",
      "source": "wikipedia",
      "source_url": "https://zh.wikipedia.org/wiki/%E7%8C%AA%E8%A1%80%E4%B8%B8%E5%AD%90",
      "timestamp": "2024-11-24T13:29:28.204767"
    }
  },
  {
    "id": "recipe_20241124_132929",
    "content": "Title: 剁椒鱼头\nChinese Name: 剁椒鱼头\nEnglish Name: 剁椒鱼头\nCuisine Type: 湘菜（湖南）\n\n剁椒魚頭，是中國八大菜系之一——湘菜的代表菜色。該菜以大魚魚頭，輔以湖南特色調味料剁辣椒，一同蒸熟即可。剁椒魚頭味辣、偏鹹鮮，尤以湖南湘潭所作最為出名。菜品色泽红亮、味浓、肉质细嫩。肥而不腻、口感软糯、鲜辣适口",
    "metadata": {
      "cuisine_type": "湘菜（湖南）",
      "dish_name": "剁椒鱼头",
      "english_name": "剁椒鱼头",
      "source": "wikipedia",
      "source_url": "https://zh.wikipedia.org/wiki/%E5%89%81%E6%A4%92%E9%B1%BC%E5%A4%B4",
      "timestamp": "2024-11-24T13:29:29.745446"
    }
  },
  {
    "id": "recipe_20241124_132931",
    "content": "Title: 糖藕\nChinese Name: 桂花糖藕\nEnglish Name: 桂花糖藕\nCuisine Type: 上海菜\n\n糖藕，或称甜藕、糯米藕、江米藕、瓤藕等，是一种发源于太湖周边地区、流行于中国各地的甜味食物，用莲藕、糯米（江米）、食糖等制作而成。",
    "metadata": {
      "cuisine_type": "上海菜",
      "dish_name": "桂花糖藕",
      "english_name": "桂花糖藕",
      "source": "wikipedia",
      "source_url": "https://zh.wikipedia.org/wiki/%E7%B3%96%E8%97%95",
      "timestamp": "2024-11-24T13:29:31.223323"
    }
  },
  {
    "id": "recipe_20241124_132932",
    "content": "Title: 扣肉\nChinese Name: 梅菜扣肉\nEnglish Name: 梅菜扣肉\nCuisine Type: 客家菜\n\n扣肉是一道用猪肉、牛肉或羊肉蒸制成的中國南方菜肴。扣肉的「扣」是指當肉蒸至熟透後，最后将其倒蓋於盤中的過程。通常作法有芋頭扣肉及梅菜扣肉。另外扣肉罐头也是一种常见的罐装食品，罐头内的卤汁是果冻状的。川菜三蒸九扣中燒白等菜餚與扣肉相當。",
    "metadata": {
      "cuisine_type": "客家菜",
      "dish_name": "梅菜扣肉",
      "english_name": "梅菜扣肉",
      "source": "wikipedia",
      "source_url": "https://zh.wikipedia.org/wiki/%E6%89%A3%E8%82%89",
      "timestamp": "2024-11-24T13:29:32.913354"
    }
  },
  {
    "id": "recipe_20241124_132934",
    "content": "Title: 红烧牛肉\nChinese Name: 红烧牛肉\nEnglish Name: 红烧牛肉\nCuisine Type: 云南菜\n\n红烧牛肉是一道常见的家常菜菜名，主料是牛肉。这道菜味道香浓，而且营养丰富，主要是因为牛肉对人体有益，可以补气、健脾胃，促进人体肌肉的生长。根据配料的不同，红烧牛肉也有很多种，如馬鈴薯烧牛肉、胡萝卜烧牛肉等。",
    "metadata": {
      "cuisine_type": "云南菜",
      "dish_name": "红烧牛肉",
      "english_name": "红烧牛肉",
      "source": "wikipedia",
      "source_url": "https://zh.wikipedia.org/wiki/%E7%BA%A2%E7%83%A7%E7%89%9B%E8%82%89",
      "timestamp": "2024-11-24T13:29:34.471307"
    }
  },
  {
    "id": "recipe_20241124_132935",
    "content": "Title: 荔枝肉\nChinese Name: 荔枝肉\nEnglish Name: 荔枝肉\nCuisine Type: 闽菜（福建）\n\n荔枝肉（闽东语平话字：liĕk-chiĕ-nṳ̆k）是一道福州传统名菜，是闽菜的代表作。原料中有白色的荸荠和切成十字花刀的猪瘦肉，烹调后因外形型似荔枝而得名。",
    "metadata": {
      "cuisine_type": "闽菜（福建）",
      "dish_name": "荔枝肉",
      "english_name": "荔枝肉",
      "source": "wikipedia",
      "source_url": "https://zh.wikipedia.org/wiki/%E8%8D%94%E6%9E%9D%E8%82%89",
      "timestamp": "2024-11-24T13:29:35.987142"
    }
  },
  {
    "id": "recipe_20241124_132937",
    "content": "Title: 薑母鴨\nChinese Name: 姜母鸭\nEnglish Name: 姜母鸭\nCuisine Type: 闽菜（福建）\n\n薑母鴨是台灣、福建廈門及泉州的一道傳統鴨肉料理。",
    "metadata": {
      "cuisine_type": "闽菜（福建）",
      "dish_name": "姜母鸭",
      "english_name": "姜母鸭",
      "source": "wikipedia",
      "source_url": "https://zh.wikipedia.org/wiki/%E8%96%91%E6%AF%8D%E9%B4%A8",
      "timestamp": "2024-11-24T13:29:37.660500"
    }
  },
  {
    "id": "recipe_20241124_132939",
    "content": "Title: 同安区\nChinese Name: 同安封肉\nEnglish Name: 同安封肉\nCuisine Type: 闽菜（福建）\n\n同安区是中国福建省厦门市的一个市辖区，原为同安县，别称“银城”、“銀同”，地处闽省东南沿海、“闽南金三角”的核心地带，區政府駐祥平街道银湖中路1号。",
    "metadata": {
      "cuisine_type": "闽菜（福建）",
      "dish_name": "同安封肉",
      "english_name": "同安封肉",
      "source": "wikipedia",
      "source_url": "https://zh.wikipedia.org/wiki/%E5%90%8C%E5%AE%89%E5%8C%BA",
      "timestamp": "2024-11-24T13:29:39.220644"
    }
  },
  {
    "id": "recipe_20241124_132940",
    "content": "Title: 白切雞\nChinese Name: 白切鸡\nEnglish Name: 白切鸡\nCuisine Type: 上海本帮菜\n\n白切雞又稱白斬雞、三黃雞、白鏨雞，是一道華人的雞肉料理，起源于广东，是粵菜的傳統菜色，因為其熟烹方式為白灼（清水煮），所以也叫做白灼雞。在香港被視為一種廣東燒味，常在燒味店有售。 白切雞的特色是烹調時不加入香料調味，把雞宰殺後用熱水浸熟或隔水蒸熟而成，過程中不加入香料和調味品，或只使用很少的調味。目的是讓雞的自然鮮味盡量顯露，這種烹調方法正好凸顯廣東菜追求保持食材原汁原味的特色。白切雞在香港、廣東、广西和海南等地都十分常見。",
    "metadata": {
      "cuisine_type": "上海本帮菜",
      "dish_name": "白切鸡",
      "english_name": "白切鸡",
      "source": "wikipedia",
      "source_url": "https://zh.wikipedia.org/wiki/%E7%99%BD%E5%88%87%E9%9B%9E",
      "timestamp": "2024-11-24T13:29:40.724690"
    }
  },
  {
    "id": "recipe_20241124_132942",
    "content": "Title: 西湖醋鱼\nChinese Name: 西湖醋鱼\nEnglish Name: 西湖醋鱼\nCuisine Type: 浙菜（浙江）\n\n西湖醋鱼，又名叔嫂传珍、宋嫂鱼，杭帮菜特色菜肴之一，以楼外楼酒店的最为有名。西湖醋鱼是杭州游客最常点的菜肴之一，但是由于做工讲究，杭州各家餐馆做出的醋鱼口味差别较大，食客评价一直以来具有争议。",
    "metadata": {
      "cuisine_type": "浙菜（浙江）",
      "dish_name": "西湖醋鱼",
      "english_name": "西湖醋鱼",
      "source": "wikipedia",
      "source_url": "https://zh.wikipedia.org/wiki/%E8%A5%BF%E6%B9%96%E9%86%8B%E9%B1%BC",
      "timestamp": "2024-11-24T13:29:42.501941"
    }
  },
  {
    "id": "recipe_20241124_132944",
    "content": "Title: 温岭市\nChinese Name: 黄鱼烧年糕\nEnglish Name: 黄鱼烧年糕\nCuisine Type: 浙菜（浙江）\n\n温岭市是中华人民共和国浙江省台州市代管的县级市。温岭地处浙江东南沿海，长三角地区的南翼，三面临海，东边与东海相连，南边与玉环市相邻，西边与乐清市及乐清湾相邻，北边与台州市区相连。全市岛屿170个，海岸线长317公里，滩涂面积为155平方公里，距省会杭州300公里，全境“四山一水五分田”，是著名的温黄平原所在地，素称“鱼米之乡”，被誉为“虾仁王国”。 温岭历史悠久，早在新石器时期，就有人类居住。明成化五年，置太平县，1914年更名为温岭，1994年撤县设市，始称温岭市。温岭建县伊始，直至2006年治府设在今太平街道方城路58号。2006年市政府迁址太平街道人民东路258号新行政中心。改革开放以来，温岭经济社会发展迅速，各项事业取得长足进步，先后获得国家级荣誉。",
    "metadata": {
      "cuisine_type": "浙菜（浙江）",
      "dish_name": "黄鱼烧年糕",
      "english_name": "黄鱼烧年糕",
      "source": "wikipedia",
      "source_url": "https://zh.wikipedia.org/wiki/%E6%B8%A9%E5%B2%AD%E5%B8%82",
      "timestamp": "2024-11-24T13:29:44.027312"
    }
  },
  {
    "id": "recipe_20241124_132945",
    "content": "Title: 龙井虾仁\nChinese Name: 龙井虾仁\nEnglish Name: 龙井虾仁\nCuisine Type: 浙菜（浙江）\n\n龙井虾仁是浙江杭州的一道特色名菜，以龙井茶叶与河虾仁为主料烹制而成，有茶叶的清香与虾的鲜美。 杭州楼外楼是制作龙井虾仁的名店。",
    "metadata": {
      "cuisine_type": "浙菜（浙江）",
      "dish_name": "龙井虾仁",
      "english_name": "龙井虾仁",
      "source": "wikipedia",
      "source_url": "https://zh.wikipedia.org/wiki/%E9%BE%99%E4%BA%95%E8%99%BE%E4%BB%81",
      "timestamp": "2024-11-24T13:29:45.535001"
    }
  },
  {
    "id": "recipe_20241124_132947",
    "content": "Title: 揚州炒飯\nChinese Name: 扬州炒饭\nEnglish Name: 扬州炒饭\nCuisine Type: 浙菜（浙江）\n\n扬州炒饭是一种源于中国并冠名为“扬州”的炒饭，根据其来源和制作形式而在各地区有所差异。",
    "metadata": {
      "cuisine_type": "浙菜（浙江）",
      "dish_name": "扬州炒饭",
      "english_name": "扬州炒饭",
      "source": "wikipedia",
      "source_url": "https://zh.wikipedia.org/wiki/%E6%8F%9A%E5%B7%9E%E7%82%92%E9%A3%AF",
      "timestamp": "2024-11-24T13:29:47.182754"
    }
  },
  {
    "id": "recipe_20241124_132948",
    "content": "Title: 泰式椒麻雞\nChinese Name: 椒麻鸡\nEnglish Name: 椒麻鸡\nCuisine Type: 浙菜（浙江）\n\n泰式椒麻雞是一種常見於台灣泰式餐廳的菜餚，主要透過花椒、酒與醬油來醃製去骨雞腿，裹粉油炸而成。關於其起源大致有兩種說法，一說是修改自雲南菜，另一說是在緬甸打工的雲南人在台灣所發明。 在新疆和四川也有叫作椒麻雞的菜，與台灣「泰式」椒麻雞的主要差別是不會油炸，而是水煮后淋油。",
    "metadata": {
      "cuisine_type": "浙菜（浙江）",
      "dish_name": "椒麻鸡",
      "english_name": "椒麻鸡",
      "source": "wikipedia",
      "source_url": "https://zh.wikipedia.org/wiki/%E6%B3%B0%E5%BC%8F%E6%A4%92%E9%BA%BB%E9%9B%9E",
      "timestamp": "2024-11-24T13:29:48.758484"
    }
  },
  {
    "id": "recipe_20241124_132950",
    "content": "Title: 老正兴\nChinese Name: 油爆虾\nEnglish Name: 油爆虾\nCuisine Type: 浙菜（浙江）\n\n老正兴菜馆是中国上海的一家传统餐饮名店，创始于1862年，属于苏锡菜菜馆，以制作江南河鲜著称，是中华老字号之一。菜餚有银鱼炒蛋、油爆虾、下巴划水、腐乳肉、烧圈子、砂锅鱼头、炒鳝糊等。 老正兴总店位于黄浦区福州路556号(原在山东路) ，另在靜安区共和新路设有分店。 2016年起，老正兴连续多年被《米其林指南》评为一星级餐厅。",
    "metadata": {
      "cuisine_type": "浙菜（浙江）",
      "dish_name": "油爆虾",
      "english_name": "油爆虾",
      "source": "wikipedia",
      "source_url": "https://zh.wikipedia.org/wiki/%E8%80%81%E6%AD%A3%E5%85%B4",
      "timestamp": "2024-11-24T13:29:50.235003"
    }
  },
  {
    "id": "recipe_20241124_132951",
    "content": "Title: 锅包肉\nChinese Name: 锅包肉\nEnglish Name: 锅包肉\nCuisine Type: 东北菜 （黑龙江等地）\n\n锅包肉原称“锅爆肉”。是一道起源于哈尔滨的东北菜。以猪肉为主料，清真风味的餐馆则用牛肉替代猪肉。做法分为老式和新式。",
    "metadata": {
      "cuisine_type": "东北菜 （黑龙江等地）",
      "dish_name": "锅包肉",
      "english_name": "锅包肉",
      "source": "wikipedia",
      "source_url": "https://zh.wikipedia.org/wiki/%E9%94%85%E5%8C%85%E8%82%89",
      "timestamp": "2024-11-24T13:29:51.751069"
    }
  },
  {
    "id": "recipe_20241124_132953",
    "content": "Title: 拉皮\nChinese Name: 拉皮\nEnglish Name: 拉皮\nCuisine Type: 东北菜 （黑龙江等地）\n\n拉皮（法語：La Puye，法语发音：[la pɥi]）是法国新阿基坦大区维埃纳省的一个市镇，位于该省东部偏北，属于沙泰勒罗区。",
    "metadata": {
      "cuisine_type": "东北菜 （黑龙江等地）",
      "dish_name": "拉皮",
      "english_name": "拉皮",
      "source": "wikipedia",
      "source_url": "https://zh.wikipedia.org/wiki/%E6%8B%89%E7%9A%AE",
      "timestamp": "2024-11-24T13:29:53.478523"
    }
  },
  {
    "id": "recipe_20241124_132955",
    "content": "Title: 内蒙古自治区\nChinese Name: 大碴子粥\nEnglish Name: 大碴子粥\nCuisine Type: 东北菜 （黑龙江等地）\n\n内蒙古自治区（蒙古语：ᠥᠪᠥᠷᠮᠣᠩᠭᠣᠯ ‍ᠤᠨᠥᠪᠡᠷᠲᠡᠭᠡᠨᠵᠠᠰᠠᠬᠤᠣᠷᠣᠨ，中蒙通用转写：Öbör Monggol-un Öbertegen J̌asaxu Oron，西里尔字母：Өвөр Монголын Өөртөө Засах Орон），法定简称内蒙古（蒙古语：ᠥᠪᠥᠷ ᠮᠣᠩᠭᠣᠯ，中蒙通用转写：Öbör Monggol，西里尔字母：Өвөр Монгол），机动车牌单字简称蒙，是中华人民共和国北部的一个自治区，地处中国北部，东北部与黑龙江、吉林、辽宁、河北交界，南部与山西、陕西、宁夏相邻，西南部与甘肃毗连，北部与蒙古國、俄罗斯接壤，自治区人民政府駐呼和浩特市敕勒川大街1号。",
    "metadata": {
      "cuisine_type": "东北菜 （黑龙江等地）",
      "dish_name": "大碴子粥",
      "english_name": "大碴子粥",
      "source": "wikipedia",
      "source_url": "https://zh.wikipedia.org/wiki/%E5%86%85%E8%92%99%E5%8F%A4%E8%87%AA%E6%B2%BB%E5%8C%BA",
      "timestamp": "2024-11-24T13:29:55.079468"
    }
  },
  {
    "id": "recipe_20241124_132956",
    "content": "Title: 内蒙古菜\nChinese Name: 内蒙烤全羊\nEnglish Name: 内蒙烤全羊\nCuisine Type: 内蒙菜 （内蒙古）\n\n内蒙古菜（简称蒙菜）是内蒙古境內的蒙古族民族特色菜系，風格粗犷豪放，多以牛羊肉、奶及面食为主要菜点原料。烹调方法相对简单，以烧烤为主，还有炖、蒸、涮等。",
    "metadata": {
      "cuisine_type": "内蒙菜 （内蒙古）",
      "dish_name": "内蒙烤全羊",
      "english_name": "内蒙烤全羊",
      "source": "wikipedia",
      "source_url": "https://zh.wikipedia.org/wiki/%E5%86%85%E8%92%99%E5%8F%A4%E8%8F%9C",
      "timestamp": "2024-11-24T13:29:56.617728"
    }
  },
  {
    "id": "recipe_20241124_132958",
    "content": "Title: 鸭血粉丝汤\nChinese Name: 鸭血粉丝汤\nEnglish Name: 鸭血粉丝汤\nCuisine Type: 其他\n\n鸭血粉丝汤又稱老鴨粉絲湯，是南京的一种小吃。主料是切成小块的鸭血、鴨肝、鴨腸，配以油豆腐和粉丝，以熬制的鲜鸭汤为汤底。",
    "metadata": {
      "cuisine_type": "其他",
      "dish_name": "鸭血粉丝汤",
      "english_name": "鸭血粉丝汤",
      "source": "wikipedia",
      "source_url": "https://zh.wikipedia.org/wiki/%E9%B8%AD%E8%A1%80%E7%B2%89%E4%B8%9D%E6%B1%A4",
      "timestamp": "2024-11-24T13:29:58.351421"
    }
  },
  {
    "id": "recipe_20241124_132959",
    "content": "Title: 酒釀圓子\nChinese Name: 酒酿圆子\nEnglish Name: 酒酿圆子\nCuisine Type: 其他\n\n酒釀圓子，又稱酒釀丸子、酒釀湯圓、酒釀水子，云南称为白酒湯圓，是一種與醪糟同吃的湯圓。廣泛流行於中國長江流域及臺灣。做法是，先用糯米和好后搓成细长型的条状，再切成一厘米大小的圆子。随后將酒酿兌水燒開，放入圆子，待圆子浮起即熟，在一些时令可以加入少量桂花。酒酿圆子清香爽口，有酒味但不濃烈。另外，在酒酿圆子中打入鸡蛋制成水铺蛋也是通常的吃法之一。 另有一派作法是待湯圓熟透，於熄火前後再行加入酒釀，認為過度加熱影響其營養價值，且酒釀為發酵食品，久煮時菌種被高溫破壞，易走味導致口感不佳。更甚者則將湯圓及酒釀分煮，以求湯汁清澈。",
    "metadata": {
      "cuisine_type": "其他",
      "dish_name": "酒酿圆子",
      "english_name": "酒酿圆子",
      "source": "wikipedia",
      "source_url": "https://zh.wikipedia.org/wiki/%E9%85%92%E9%87%80%E5%9C%93%E5%AD%90",
      "timestamp": "2024-11-24T13:29:59.841523"
    }
  },
  {
    "id": "recipe_20241124_133001",
    "content": "Title: 客家酿豆腐\nChinese Name: 客家酿豆腐\nEnglish Name: 客家酿豆腐\nCuisine Type: 其他\n\n客家酿豆腐是客家三大名菜之一。 “酿”是一个客家话动词，表示“镶”或“植入馅料”的意思，“酿豆腐”即“有肉馅的豆腐”之意。",
    "metadata": {
      "cuisine_type": "其他",
      "dish_name": "客家酿豆腐",
      "english_name": "客家酿豆腐",
      "source": "wikipedia",
      "source_url": "https://zh.wikipedia.org/wiki/%E5%AE%A2%E5%AE%B6%E9%85%BF%E8%B1%86%E8%85%90",
      "timestamp": "2024-11-24T13:30:01.335288"
    }
  },
  {
    "id": "recipe_20241124_133002",
    "content": "Title: 北京烤鸭\nChinese Name: 北京烤鸭\nEnglish Name: 北京烤鸭\nCuisine Type: 其他\n\n北京烤鸭，是源自中國北京的一道全鸭菜式，又名北京填鴨（烤鸭是道菜，填鸭是使用的原料，是指用强制喂食方法养大的北京鸭）。北京烤鸭分为「挂炉烤鸭」与「焖炉烤鸭」两大流派，北京的老字号烤鸭店全聚德主打挂炉烤鸭，便宜坊則主打焖炉烤鸭。北京其他著名的烤鸭店還有大董、长安壹号、1949全鸭季、利群、四季民福和花家怡园等。",
    "metadata": {
      "cuisine_type": "其他",
      "dish_name": "北京烤鸭",
      "english_name": "北京烤鸭",
      "source": "wikipedia",
      "source_url": "https://zh.wikipedia.org/wiki/%E5%8C%97%E4%BA%AC%E7%83%A4%E9%B8%AD",
      "timestamp": "2024-11-24T13:30:02.881257"
    }
  }
]